cfgrw/__init__.py
cfgrw/formats/__init__.py
cfgrw/formats/envvar.py
cfgrw/formats/ini.py
cfgrw/formats/json.py
cfgrw/formats/xml.py
cfgrw/formats/yaml.py
cfgrw-1.0.0.dist-info/LICENSE
cfgrw-1.0.0.dist-info/METADATA
cfgrw-1.0.0.dist-info/WHEEL
cfgrw-1.0.0.dist-info/RECORD
