Metadata-Version: 2.3
Name: cfgrw
Version: 1.0.0
Summary: Python library for reading and writing properties in configuration files
License: Apache-2.0
Keywords: cfgrw,configuration
Author: Cliffano Subagio
Author-email: cliffano@gmail.com
Requires-Python: >=3.10,<4.0
Classifier: License :: OSI Approved :: Apache Software License
Classifier: Operating System :: OS Independent
Classifier: Programming Language :: Python :: 3
Classifier: Programming Language :: Python :: 3.10
Classifier: Programming Language :: Python :: 3.11
Classifier: Programming Language :: Python :: 3.12
Classifier: Programming Language :: Python :: 3.13
Requires-Dist: Jinja2 (>=3.1.2,<4.0.0)
Requires-Dist: PyYAML (>=6.0.2,<6.1.0)
Project-URL: Documentation, https://github.com/cliffano/cfg-rw
Project-URL: Homepage, https://github.com/cliffano/cfg-rw
Project-URL: Repository, https://github.com/cliffano/cfg-rw
